MANIFEST.in
README.md
requirements.txt
setup.py
lfs_gallery/__init__.py
lfs_gallery/admin.py
lfs_gallery/models.py
lfs_gallery/urls.py
lfs_gallery/views.py
lfs_gallery.egg-info/PKG-INFO
lfs_gallery.egg-info/SOURCES.txt
lfs_gallery.egg-info/dependency_links.txt
lfs_gallery.egg-info/not-zip-safe
lfs_gallery.egg-info/requires.txt
lfs_gallery.egg-info/top_level.txt
lfs_gallery/templates/gallery.html
lfs_gallery/templates/manage/add_gallery.html
lfs_gallery/templates/manage/add_gallery_item.html
lfs_gallery/templates/manage/gallery_item.html
lfs_gallery/templates/manage/gallery/base.html
lfs_gallery/templates/manage/gallery/navigation.html
lfs_gallery/templatetags/__init__.py
lfs_gallery/templatetags/gallery.py