Metadata-Version: 1.0
Name: lfs-gallery
Version: 0.1.5
Summary: Image Gallery for LFS
Home-page: http://github.com/suvit/lfs-gallery
Author: Victor Safronovich
Author-email: vsafronovich@gmail.com
License: MIT
Platform: UNKNOWN
